[
  {
    "position": 1,
    "equipe": "Good Cheese",
    "joueur": "",
    "temps": "201:06:07",
    "ecart": "+0:00:00"
  },
  {
    "position": 20,
    "equipe": "Doping",
    "joueur": "",
    "temps": "202:34:26",
    "ecart": "+1:28:19"
  },
  {
    "position": 7,
    "equipe": "UCPSPA",
    "joueur": "",
    "temps": "201:37:35",
    "ecart": "+0:31:28"
  },
  {
    "position": 9,
    "equipe": "Daikin",
    "joueur": "",
    "temps": "201:41:55",
    "ecart": "+0:35:48"
  },
  {
    "position": 14,
    "equipe": "Team Gouda",
    "joueur": "",
    "temps": "202:18:24",
    "ecart": "+1:12:17"
  },
  {
    "position": 3,
    "equipe": "Bier Brigade",
    "joueur": "Bismuth",
    "temps": "201:24:12",
    "ecart": "+0:18:05"
  },
  {
    "position": 4,
    "equipe": "RnB de Rue",
    "joueur": "",
    "temps": "201:25:28",
    "ecart": "+0:19:21"
  },
  {
    "position": 13,
    "equipe": "Team Alençon",
    "joueur": "",
    "temps": "202:13:15",
    "ecart": "+1:07:08"
  },
  {
    "position": 2,
    "equipe": "Froooonce",
    "joueur": "",
    "temps": "201:17:04",
    "ecart": "+0:10:57"
  },
  {
    "position": 10,
    "equipe": "Big Farma",
    "joueur": "",
    "temps": "201:45:02",
    "ecart": "+0:38:55"
  },
  {
    "position": 18,
    "equipe": "Team Burrata",
    "joueur": "",
    "temps": "202:30:32",
    "ecart": "+1:24:25"
  },
  {
    "position": 23,
    "equipe": "20 Rouge",
    "joueur": "",
    "temps": "203:09:20",
    "ecart": "+2:03:13"
  },
  {
    "position": 11,
    "equipe": "Viesmann",
    "joueur": "",
    "temps": "202:02:55",
    "ecart": "+0:56:48"
  },
  {
    "position": 5,
    "equipe": "Team Claquos",
    "joueur": "",
    "temps": "201:32:09",
    "ecart": "+0:26:02"
  },
  {
    "position": 12,
    "equipe": "Österreichisches Bier",
    "joueur": "",
    "temps": "202:04:07",
    "ecart": "+0:58:00"
  },
  {
    "position": 17,
    "equipe": "Suceurs 2 Roues",
    "joueur": "",
    "temps": "202:24:39",
    "ecart": "+1:18:32"
  },
  {
    "position": 6,
    "equipe": "Saunier Duval",
    "joueur": "",
    "temps": "201:32:47",
    "ecart": "+0:26:40"
  },
  {
    "position": 22,
    "equipe": "Weed",
    "joueur": "",
    "temps": "202:55:50",
    "ecart": "+1:49:43"
  },
  {
    "position": 8,
    "equipe": "Gangster and Gentleman",
    "joueur": "",
    "temps": "201:39:34",
    "ecart": "+0:33:27"
  },
  {
    "position": 19,
    "equipe": "Over Dose Racing",
    "joueur": "",
    "temps": "202:33:33",
    "ecart": "+1:27:26"
  },
  {
    "position": 15,
    "equipe": "Frisquet",
    "joueur": "",
    "temps": "202:20:13",
    "ecart": "+1:14:06"
  },
  {
    "position": 16,
    "equipe": "Rap Street Boys",
    "joueur": "",
    "temps": "202:23:47",
    "ecart": "+1:17:40"
  },
  {
    "position": 24,
    "equipe": "Nederlands Bier",
    "joueur": "",
    "temps": "203:41:14",
    "ecart": "+2:35:07"
  },
  {
    "position": 21,
    "equipe": "Belgisch Bier",
    "joueur": "",
    "temps": "202:43:49",
    "ecart": "+1:37:42"
  }
]